odoo/addons/product_gtin/README.rst
odoo/addons/product_gtin/__init__.py
odoo/addons/product_gtin/__manifest__.py
odoo/addons/product_gtin/i18n/fr.po
odoo/addons/product_gtin/i18n/product_gtin.pot
odoo/addons/product_gtin/models/__init__.py
odoo/addons/product_gtin/models/barcode_gtin_check_mixin.py
odoo/addons/product_gtin/models/product_product.py
odoo/addons/product_gtin/models/res_company.py
odoo/addons/product_gtin/models/res_config_settings.py
odoo/addons/product_gtin/readme/CONTRIBUTORS.rst
odoo/addons/product_gtin/readme/DESCRIPTION.rst
odoo/addons/product_gtin/static/description/icon.png
odoo/addons/product_gtin/static/description/index.html
odoo/addons/product_gtin/tests/__init__.py
odoo/addons/product_gtin/tests/test_product_gtin_functions.py
odoo/addons/product_gtin/views/res_config_settings_views.xml
odoo13_addon_product_gtin-13.0.1.0.1.dev5.dist-info/METADATA
odoo13_addon_product_gtin-13.0.1.0.1.dev5.dist-info/WHEEL
odoo13_addon_product_gtin-13.0.1.0.1.dev5.dist-info/top_level.txt
odoo13_addon_product_gtin-13.0.1.0.1.dev5.dist-info/RECORD
