Metadata-Version: 2.1
Name: odoo13-addon-product-gtin
Version: 13.0.1.0.1.dev5
Summary: This module provides checks and management to EAN codes
Home-page: https://github.com/OCA/stock-logistics-barcode
Author: ChriCar Beteiligungs- und Beratungs- GmbH, Odoo Community Association (OCA), ACSONE SA/NV
Author-email: support@odoo-community.org
License: AGPL-3
Platform: UNKNOWN
Classifier: Programming Language :: Python
Classifier: Framework :: Odoo
Classifier: Framework :: Odoo :: 13.0
Classifier: License :: OSI Approved :: GNU Affero General Public License v3
Requires-Python: >=3.5
Requires-Dist: barcodenumber
Requires-Dist: odoo <13.1dev,>=13.0a
